solvusoftlib/__init__.py
solvusoftlib/application.py
solvusoftlib/company.py
solvusoftlib/extensions.py
solvusoft-0.1.2.dist-info/METADATA
solvusoft-0.1.2.dist-info/WHEEL
solvusoft-0.1.2.dist-info/top_level.txt
solvusoft-0.1.2.dist-info/RECORD
