Metadata-Version: 2.1
Name: solvusoft
Version: 0.1.2
Summary: Solvusoft Library
Home-page: https://github.com/XieZheyuan/solvusoftlib
Author: Xie Zheyuan
Author-email: billy03282@163.com
License: UNKNOWN
Platform: all
Classifier: Programming Language :: Python
Classifier: Programming Language :: Python :: 3
Classifier: Programming Language :: Python :: 3.4
Classifier: Programming Language :: Python :: 3.5
Classifier: Programming Language :: Python :: 3.6
Classifier: Topic :: Software Development :: Libraries
Requires-Dist: requests
Requires-Dist: beautifulsoup4
